{"dependencies":[{"name":"/Users/chasewillden/Documents/dev/IlluminateLms/IlluminateLms.Web/package.json","includedInParent":true,"mtime":1520918800220},{"name":"/Users/chasewillden/Documents/dev/IlluminateLms/IlluminateLms.Web/tsconfig.json","includedInParent":true,"mtime":1520146993688},{"name":"react","loc":{"line":3,"column":20}},{"name":"react-router-dom","loc":{"line":4,"column":33}}],"generated":{"js":"\"use strict\";\n\nObject.defineProperty(exports, \"__esModule\", { value: true });\nvar React = require(\"react\");\nvar react_router_dom_1 = require(\"react-router-dom\");\nvar RoleList = function RoleList(props) {\n    return React.createElement(\"div\", null, React.createElement(\"legend\", { className: \"uk-legend\" }, \"Roles\"), React.createElement(\"ul\", { className: 'uk-list' }, props.roles.map(function (role) {\n        return React.createElement(\"li\", { key: role.roleId }, React.createElement(react_router_dom_1.NavLink, { to: '/roles/selected/' + role.roleId }, role.name));\n    })));\n};\nexports.default = RoleList;","map":{"mappings":[{"source":"Components/Admin/People/SelectedUser/RoleList.tsx","name":null,"original":{"line":1,"column":0},"generated":{"line":4,"column":0}},{"source":"Components/Admin/People/SelectedUser/RoleList.tsx","name":null,"original":{"line":1,"column":0},"generated":{"line":4,"column":4}},{"source":"Components/Admin/People/SelectedUser/RoleList.tsx","name":null,"original":{"line":1,"column":0},"generated":{"line":4,"column":12}},{"source":"Components/Admin/People/SelectedUser/RoleList.tsx","name":null,"original":{"line":1,"column":0},"generated":{"line":4,"column":20}},{"source":"Components/Admin/People/SelectedUser/RoleList.tsx","name":null,"original":{"line":1,"column":0},"generated":{"line":4,"column":27}},{"source":"Components/Admin/People/SelectedUser/RoleList.tsx","name":null,"original":{"line":1,"column":0},"generated":{"line":4,"column":28}},{"source":"Components/Admin/People/SelectedUser/RoleList.tsx","name":null,"original":{"line":2,"column":0},"generated":{"line":5,"column":0}},{"source":"Components/Admin/People/SelectedUser/RoleList.tsx","name":null,"original":{"line":2,"column":0},"generated":{"line":5,"column":4}},{"source":"Components/Admin/People/SelectedUser/RoleList.tsx","name":null,"original":{"line":2,"column":0},"generated":{"line":5,"column":25}},{"source":"Components/Admin/People/SelectedUser/RoleList.tsx","name":null,"original":{"line":2,"column":0},"generated":{"line":5,"column":33}},{"source":"Components/Admin/People/SelectedUser/RoleList.tsx","name":null,"original":{"line":2,"column":0},"generated":{"line":5,"column":51}},{"source":"Components/Admin/People/SelectedUser/RoleList.tsx","name":null,"original":{"line":2,"column":0},"generated":{"line":5,"column":52}},{"source":"Components/Admin/People/SelectedUser/RoleList.tsx","name":null,"original":{"line":5,"column":0},"generated":{"line":6,"column":0}},{"source":"Components/Admin/People/SelectedUser/RoleList.tsx","name":null,"original":{"line":5,"column":6},"generated":{"line":6,"column":4}},{"source":"Components/Admin/People/SelectedUser/RoleList.tsx","name":null,"original":{"line":5,"column":17},"generated":{"line":6,"column":15}},{"source":"Components/Admin/People/SelectedUser/RoleList.tsx","name":null,"original":{"line":5,"column":6},"generated":{"line":6,"column":24}},{"source":"Components/Admin/People/SelectedUser/RoleList.tsx","name":null,"original":{"line":5,"column":17},"generated":{"line":6,"column":32}},{"source":"Components/Admin/People/SelectedUser/RoleList.tsx","name":null,"original":{"line":5,"column":18},"generated":{"line":6,"column":33}},{"source":"Components/Admin/People/SelectedUser/RoleList.tsx","name":null,"original":{"line":5,"column":17},"generated":{"line":6,"column":38}},{"source":"Components/Admin/People/SelectedUser/RoleList.tsx","name":null,"original":{"line":5,"column":28},"generated":{"line":6,"column":40}},{"source":"Components/Admin/People/SelectedUser/RoleList.tsx","name":null,"original":{"line":5,"column":33},"generated":{"line":7,"column":0}},{"source":"Components/Admin/People/SelectedUser/RoleList.tsx","name":null,"original":{"line":6,"column":2},"generated":{"line":7,"column":11}},{"source":"Components/Admin/People/SelectedUser/RoleList.tsx","name":null,"original":{"line":6,"column":2},"generated":{"line":7,"column":17}},{"source":"Components/Admin/People/SelectedUser/RoleList.tsx","name":null,"original":{"line":6,"column":2},"generated":{"line":7,"column":30}},{"source":"Components/Admin/People/SelectedUser/RoleList.tsx","name":null,"original":{"line":6,"column":2},"generated":{"line":7,"column":31}},{"source":"Components/Admin/People/SelectedUser/RoleList.tsx","name":null,"original":{"line":6,"column":2},"generated":{"line":7,"column":36}},{"source":"Components/Admin/People/SelectedUser/RoleList.tsx","name":null,"original":{"line":6,"column":2},"generated":{"line":7,"column":38}},{"source":"Components/Admin/People/SelectedUser/RoleList.tsx","name":null,"original":{"line":6,"column":2},"generated":{"line":7,"column":42}},{"source":"Components/Admin/People/SelectedUser/RoleList.tsx","name":null,"original":{"line":7,"column":4},"generated":{"line":7,"column":44}},{"source":"Components/Admin/People/SelectedUser/RoleList.tsx","name":null,"original":{"line":7,"column":4},"generated":{"line":7,"column":50}},{"source":"Components/Admin/People/SelectedUser/RoleList.tsx","name":null,"original":{"line":7,"column":4},"generated":{"line":7,"column":63}},{"source":"Components/Admin/People/SelectedUser/RoleList.tsx","name":null,"original":{"line":7,"column":4},"generated":{"line":7,"column":64}},{"source":"Components/Admin/People/SelectedUser/RoleList.tsx","name":null,"original":{"line":7,"column":4},"generated":{"line":7,"column":72}},{"source":"Components/Admin/People/SelectedUser/RoleList.tsx","name":null,"original":{"line":7,"column":4},"generated":{"line":7,"column":74}},{"source":"Components/Admin/People/SelectedUser/RoleList.tsx","name":null,"original":{"line":7,"column":12},"generated":{"line":7,"column":76}},{"source":"Components/Admin/People/SelectedUser/RoleList.tsx","name":null,"original":{"line":7,"column":22},"generated":{"line":7,"column":87}},{"source":"Components/Admin/People/SelectedUser/RoleList.tsx","name":null,"original":{"line":7,"column":4},"generated":{"line":7,"column":98}},{"source":"Components/Admin/People/SelectedUser/RoleList.tsx","name":null,"original":{"line":7,"column":4},"generated":{"line":7,"column":100}},{"source":"Components/Admin/People/SelectedUser/RoleList.tsx","name":null,"original":{"line":7,"column":33},"generated":{"line":7,"column":102}},{"source":"Components/Admin/People/SelectedUser/RoleList.tsx","name":null,"original":{"line":7,"column":4},"generated":{"line":7,"column":109}},{"source":"Components/Admin/People/SelectedUser/RoleList.tsx","name":null,"original":{"line":6,"column":2},"generated":{"line":7,"column":110}},{"source":"Components/Admin/People/SelectedUser/RoleList.tsx","name":null,"original":{"line":8,"column":4},"generated":{"line":7,"column":112}},{"source":"Components/Admin/People/SelectedUser/RoleList.tsx","name":null,"original":{"line":8,"column":4},"generated":{"line":7,"column":118}},{"source":"Components/Admin/People/SelectedUser/RoleList.tsx","name":null,"original":{"line":8,"column":4},"generated":{"line":7,"column":131}},{"source":"Components/Admin/People/SelectedUser/RoleList.tsx","name":null,"original":{"line":8,"column":4},"generated":{"line":7,"column":132}},{"source":"Components/Admin/People/SelectedUser/RoleList.tsx","name":null,"original":{"line":8,"column":4},"generated":{"line":7,"column":136}},{"source":"Components/Admin/People/SelectedUser/RoleList.tsx","name":null,"original":{"line":8,"column":4},"generated":{"line":7,"column":138}},{"source":"Components/Admin/People/SelectedUser/RoleList.tsx","name":null,"original":{"line":8,"column":8},"generated":{"line":7,"column":140}},{"source":"Components/Admin/People/SelectedUser/RoleList.tsx","name":null,"original":{"line":8,"column":18},"generated":{"line":7,"column":151}},{"source":"Components/Admin/People/SelectedUser/RoleList.tsx","name":null,"original":{"line":8,"column":4},"generated":{"line":7,"column":160}},{"source":"Components/Admin/People/SelectedUser/RoleList.tsx","name":null,"original":{"line":8,"column":4},"generated":{"line":7,"column":162}},{"source":"Components/Admin/People/SelectedUser/RoleList.tsx","name":null,"original":{"line":9,"column":7},"generated":{"line":7,"column":164}},{"source":"Components/Admin/People/SelectedUser/RoleList.tsx","name":null,"original":{"line":9,"column":13},"generated":{"line":7,"column":170}},{"source":"Components/Admin/People/SelectedUser/RoleList.tsx","name":null,"original":{"line":9,"column":7},"generated":{"line":7,"column":175}},{"source":"Components/Admin/People/SelectedUser/RoleList.tsx","name":null,"original":{"line":9,"column":19},"generated":{"line":7,"column":176}},{"source":"Components/Admin/People/SelectedUser/RoleList.tsx","name":null,"original":{"line":9,"column":7},"generated":{"line":7,"column":179}},{"source":"Components/Admin/People/SelectedUser/RoleList.tsx","name":null,"original":{"line":9,"column":23},"generated":{"line":7,"column":180}},{"source":"Components/Admin/People/SelectedUser/RoleList.tsx","name":null,"original":{"line":9,"column":24},"generated":{"line":7,"column":190}},{"source":"Components/Admin/People/SelectedUser/RoleList.tsx","name":null,"original":{"line":9,"column":23},"generated":{"line":7,"column":194}},{"source":"Components/Admin/People/SelectedUser/RoleList.tsx","name":null,"original":{"line":9,"column":34},"generated":{"line":7,"column":196}},{"source":"Components/Admin/People/SelectedUser/RoleList.tsx","name":null,"original":{"line":9,"column":39},"generated":{"line":8,"column":0}},{"source":"Components/Admin/People/SelectedUser/RoleList.tsx","name":null,"original":{"line":10,"column":8},"generated":{"line":8,"column":15}},{"source":"Components/Admin/People/SelectedUser/RoleList.tsx","name":null,"original":{"line":10,"column":8},"generated":{"line":8,"column":21}},{"source":"Components/Admin/People/SelectedUser/RoleList.tsx","name":null,"original":{"line":10,"column":8},"generated":{"line":8,"column":34}},{"source":"Components/Admin/People/SelectedUser/RoleList.tsx","name":null,"original":{"line":10,"column":8},"generated":{"line":8,"column":35}},{"source":"Components/Admin/People/SelectedUser/RoleList.tsx","name":null,"original":{"line":10,"column":8},"generated":{"line":8,"column":39}},{"source":"Components/Admin/People/SelectedUser/RoleList.tsx","name":null,"original":{"line":10,"column":8},"generated":{"line":8,"column":41}},{"source":"Components/Admin/People/SelectedUser/RoleList.tsx","name":null,"original":{"line":10,"column":12},"generated":{"line":8,"column":43}},{"source":"Components/Admin/People/SelectedUser/RoleList.tsx","name":null,"original":{"line":10,"column":17},"generated":{"line":8,"column":48}},{"source":"Components/Admin/People/SelectedUser/RoleList.tsx","name":null,"original":{"line":10,"column":22},"generated":{"line":8,"column":53}},{"source":"Components/Admin/People/SelectedUser/RoleList.tsx","name":null,"original":{"line":10,"column":8},"generated":{"line":8,"column":59}},{"source":"Components/Admin/People/SelectedUser/RoleList.tsx","name":null,"original":{"line":10,"column":8},"generated":{"line":8,"column":61}},{"source":"Components/Admin/People/SelectedUser/RoleList.tsx","name":null,"original":{"line":11,"column":10},"generated":{"line":8,"column":63}},{"source":"Components/Admin/People/SelectedUser/RoleList.tsx","name":null,"original":{"line":11,"column":10},"generated":{"line":8,"column":69}},{"source":"Components/Admin/People/SelectedUser/RoleList.tsx","name":null,"original":{"line":11,"column":10},"generated":{"line":8,"column":82}},{"source":"Components/Admin/People/SelectedUser/RoleList.tsx","name":null,"original":{"line":11,"column":11},"generated":{"line":8,"column":83}},{"source":"Components/Admin/People/SelectedUser/RoleList.tsx","name":null,"original":{"line":11,"column":11},"generated":{"line":8,"column":102}},{"source":"Components/Admin/People/SelectedUser/RoleList.tsx","name":null,"original":{"line":11,"column":10},"generated":{"line":8,"column":109}},{"source":"Components/Admin/People/SelectedUser/RoleList.tsx","name":null,"original":{"line":11,"column":18},"generated":{"line":8,"column":111}},{"source":"Components/Admin/People/SelectedUser/RoleList.tsx","name":null,"original":{"line":11,"column":19},"generated":{"line":8,"column":113}},{"source":"Components/Admin/People/SelectedUser/RoleList.tsx","name":null,"original":{"line":11,"column":23},"generated":{"line":8,"column":117}},{"source":"Components/Admin/People/SelectedUser/RoleList.tsx","name":null,"original":{"line":11,"column":44},"generated":{"line":8,"column":138}},{"source":"Components/Admin/People/SelectedUser/RoleList.tsx","name":null,"original":{"line":11,"column":49},"generated":{"line":8,"column":143}},{"source":"Components/Admin/People/SelectedUser/RoleList.tsx","name":null,"original":{"line":11,"column":18},"generated":{"line":8,"column":149}},{"source":"Components/Admin/People/SelectedUser/RoleList.tsx","name":null,"original":{"line":11,"column":10},"generated":{"line":8,"column":151}},{"source":"Components/Admin/People/SelectedUser/RoleList.tsx","name":null,"original":{"line":11,"column":58},"generated":{"line":8,"column":153}},{"source":"Components/Admin/People/SelectedUser/RoleList.tsx","name":null,"original":{"line":11,"column":63},"generated":{"line":8,"column":158}},{"source":"Components/Admin/People/SelectedUser/RoleList.tsx","name":null,"original":{"line":11,"column":10},"generated":{"line":8,"column":162}},{"source":"Components/Admin/People/SelectedUser/RoleList.tsx","name":null,"original":{"line":10,"column":8},"generated":{"line":8,"column":163}},{"source":"Components/Admin/People/SelectedUser/RoleList.tsx","name":null,"original":{"line":9,"column":39},"generated":{"line":8,"column":164}},{"source":"Components/Admin/People/SelectedUser/RoleList.tsx","name":null,"original":{"line":13,"column":7},"generated":{"line":9,"column":0}},{"source":"Components/Admin/People/SelectedUser/RoleList.tsx","name":null,"original":{"line":9,"column":7},"generated":{"line":9,"column":5}},{"source":"Components/Admin/People/SelectedUser/RoleList.tsx","name":null,"original":{"line":8,"column":4},"generated":{"line":9,"column":6}},{"source":"Components/Admin/People/SelectedUser/RoleList.tsx","name":null,"original":{"line":6,"column":2},"generated":{"line":9,"column":7}},{"source":"Components/Admin/People/SelectedUser/RoleList.tsx","name":null,"original":{"line":5,"column":33},"generated":{"line":9,"column":8}},{"source":"Components/Admin/People/SelectedUser/RoleList.tsx","name":null,"original":{"line":16,"column":1},"generated":{"line":10,"column":0}},{"source":"Components/Admin/People/SelectedUser/RoleList.tsx","name":null,"original":{"line":5,"column":0},"generated":{"line":10,"column":1}},{"source":"Components/Admin/People/SelectedUser/RoleList.tsx","name":null,"original":{"line":18,"column":0},"generated":{"line":11,"column":0}},{"source":"Components/Admin/People/SelectedUser/RoleList.tsx","name":null,"original":{"line":18,"column":0},"generated":{"line":11,"column":8}},{"source":"Components/Admin/People/SelectedUser/RoleList.tsx","name":null,"original":{"line":18,"column":0},"generated":{"line":11,"column":15}},{"source":"Components/Admin/People/SelectedUser/RoleList.tsx","name":null,"original":{"line":18,"column":15},"generated":{"line":11,"column":18}},{"source":"Components/Admin/People/SelectedUser/RoleList.tsx","name":null,"original":{"line":18,"column":0},"generated":{"line":11,"column":26}}],"sources":{"Components/Admin/People/SelectedUser/RoleList.tsx":"import * as React from 'react'\nimport { NavLink } from 'react-router-dom';\nimport { Role } from '../../../../Models';\n\nconst RoleList = (props: any) => (\n  <div>\n    <legend className=\"uk-legend\">Roles</legend>\n    <ul className='uk-list'>\n      {props.roles.map((role: Role) => (\n        <li key={role.roleId}>\n          <NavLink to={'/roles/selected/' + role.roleId}>{role.name}</NavLink>\n        </li>\n      ))}\n    </ul>\n  </div>\n)\n\nexport default RoleList;"},"lineCount":null}},"hash":"a5e64490b0b150bb79ac701d15e52d5d","cacheData":{"env":{}}}